{"ptitle":"旧约 圣咏集","purl":"/bible/template/023","title":"旧约 圣咏集 第廿四篇上主荣进熙雍","url":"/bible/chapter/023/024.json","mp3":"/023/024.mp3","text":"<h2></h2><h3>旧约 圣咏集 第廿四篇上主荣进熙雍</h3><p class=\"s\">01.\t达味诗歌。大地和其中的万物，属於上主，世界和其间的居民，属於上主。</p><p class=\"s\">02.\t是他在海洋上奠定了大地，是他在江河上建立了全世。</p><p class=\"s\">03.\t谁能登上上主的圣山？谁能居留在他的圣殿？</p><p class=\"s\">04.\t是那手洁心清，不慕虚幻的人，是那不发假誓，不行欺骗的人。</p><p class=\"s\">05.\t他必获得上主的祝福；和拯救者天主的报酬。</p><p class=\"s\">06.\t这样的人是寻求上主的裔，追求雅各伯天主仪容子息。</p><p class=\"s\">07.\t城门，请提高你们的门楣，古老的门户，请加大门扉，因为要欢迎光荣的君王。</p><p class=\"s\">08.\t谁是这位光荣的君主？就是英勇大能的上主，是那有力作战的天主。</p><p class=\"s\">09.\t城门，请提高你们的门楣，古老的门户，请加大门扉，因为要欢迎光荣的君王，</p><p class=\"s\">10.\t谁是这位光荣的君主？其实这位光荣的君主，就是万军之军的上主。</p>"}