{"ptitle":"旧约 民长纪 Judges","purl":"/bible/template/007","title":"旧约 民长纪 Judges 第十七章","url":"/bible/chapter/007/017.json","mp3":"/007/017.mp3","text":"<h2>附录一米加的神像与丹族的迁移(17-18)</h2><h3>旧约 民长纪 Judges 第十七章</h3><p class=\"t3\">米加的母亲制造神像</p><p class=\"s\">01.\t厄弗辣因山地有一个人，名叫米加，</p><p class=\"s\">02.\t他、</p><p class=\"s\">03.\t对自己的母亲说：「有人拿去你那一千一百银钱，对这事你曾起过誓，我也亲自听见你说：我要亲手把这项银钱奉献给上主，为我儿做一尊神像。看，银钱在这，是我拿了；如今还给你!」他的母亲就说：「愿我儿蒙上主祝福!」於是米加就把一千一百银钱还给他的母亲。</p><p class=\"s\">04.\t当他把银钱还给他的母亲以后，她的母亲便拿出两百银子给了银匠，请他制造一尊神像，安放在米加的家。</p><p class=\"s\">05.\t於是米加为这尊神像盖了一座神庙。又做了「厄弗得」和「忒辣芬，」委派自己的一个儿子充任司祭。</p><p class=\"s\">06.\t当时在以色列没有君王，各人任意行事。</p><p class=\"t3\">米加收肋未为司祭</p><p class=\"s\">07.\t当时有一个少年，他是个肋未人，从猷大白冷，即从猷大支派来到那作客。</p><p class=\"s\">08.\t这人离开猷大白冷，想找一个可寄居的地方；当他旅行的时候，来到厄弗辣因山地，米加的家旁，</p><p class=\"s\">09.\t米加问他说：「你从那来？」他回答说：「我是个肋未人，由猷大白冷来，想找一个可寄居的地方。」</p><p class=\"s\">10.\t米加就对他说：「你住在我这罢!作我的师傅和司祭，我每年给你十块银钱，还照管你的吃穿。」米加挽留那肋未人，</p><p class=\"s\">11.\t他遂同意住在米加那，他看待这少年好似自己的儿子。</p><p class=\"s\">12.\t米加又委任了这肋未人，这人遂作了他的司祭，住在米加家中。</p><p class=\"s\">13.\t於是米加说：「如今我知道上主必施恩於我，因为有位肋未人作了我的司祭。」</p>"}