{"ptitle":"旧约 圣咏集","purl":"/bible/template/023","title":"旧约 圣咏集 第一四一篇求免陷诱惑和迫害","url":"/bible/chapter/023/141.json","mp3":"/023/141.mp3","text":"<h2></h2><h3>旧约 圣咏集 第一四一篇求免陷诱惑和迫害</h3><p class=\"s\">01.\t达味的圣咏。上主，我呼求你，请求速来救助我，上主，我呼求你，请你听我的呼号。</p><p class=\"s\">02.\t愿我向你行的祈祷，像馨香上升，愿我的手高举，如同晚祭的高腾。</p><p class=\"s\">03.\t上主，求你在我的口边派一守卫，求你在我的唇前派一警备。</p><p class=\"s\">04.\t莫让我的心倾向邪道，免得我再去犯罪作恶；莫让我与恶人同作坏事，免得我食他们的美味。</p><p class=\"s\">05.\t义人责打我，算是我的恩遇，他责斥我，是给我头的傅油。我的头也决不会加以抗拒，我仍然为迫害我的人祈求。</p><p class=\"s\">06.\t当他们的首领被抛於石时，感觉到我的话时是如何甘饴。</p><p class=\"s\">07.\t他们的骨头被弃置在阴府门旁，像人耕地掘田，将土块任意抛放。</p><p class=\"s\">08.\t上主天主，我的双目一直仰望你，我信赖你，不要将我的灵魂抛弃。</p><p class=\"s\">09.\t求你保护我免陷於他们为我设的网罗，求你使我能够脱离为非作歹者的圈套。</p><p class=\"s\">10.\t愿恶人一起堕入自设的网罗，而我却得以安然无恙地脱逃。</p>"}