{"ptitle":"新约 路加福音 Luke","purl":"/bible/template/049","title":"新约 路加福音 Luke 第十七章","url":"/bible/chapter/049/017.json","mp3":"/049/017.mp3","text":"<h2></h2><h3>新约 路加福音 Luke 第十七章</h3><p class=\"t3\">门徒应有的态度</p><p class=\"s\">1&nbsp;&nbsp;耶稣对门徒说：「引人跌倒的事是免不了的；但是，引人跌倒的人是有祸的。</p><p class=\"s\">2&nbsp;&nbsp;把一块磨石套在他的颈上，投入海中，比让他引这些小子中的一个跌倒，为他更好。</p><p class=\"s\">3&nbsp;&nbsp;你们要谨慎！如果你的兄弟犯了罪，你就得规劝他；他如果后悔了，你就得宽恕他。</p><p class=\"s\">4&nbsp;&nbsp;如果他一天七次得罪了你，而又七次转向你说：我后悔了，你也得宽恕他。」</p><p class=\"s\">5&nbsp;&nbsp;宗徒们向主说：「请增加我们的信德罢！」</p><p class=\"s\">6&nbsp;&nbsp;主说：「如果你们有信德像芥子那样大，即使你们给这棵桑树说：你连根拔出，移植到海中去！它也会服从你们的。</p><p class=\"s\">7&nbsp;&nbsp;你们中间谁有仆人耕田或放羊，从田地里回来，即给他说：你快过来坐下吃饭罢！</p><p class=\"s\">8&nbsp;&nbsp;而不给他说：预备我吃饭，束上腰伺候我，等我吃喝完毕，以后你才吃喝？</p><p class=\"s\">9&nbsp;&nbsp;仆人做了吩咐的事，主人岂要向他道谢？</p><p class=\"s\">10&nbsp;&nbsp;你们也是这样，既做完吩咐你们的一切，仍然要说：我们是无用的仆人，我们不过做了我们应做的事。」</p><p class=\"t3\">耶稣治好十个癞病人</p><p class=\"s\">11&nbsp;&nbsp;耶稣往耶路撒冷去的时候，经过撒玛黎雅及加里肋亚中间，</p><p class=\"s\">12&nbsp;&nbsp;走进一个村庄的时候，有十个癞病人迎面而来，远远地站着。</p><p class=\"s\">13&nbsp;&nbsp;他们提高声音说：「师傅，耶稣，可怜我们罢！」</p><p class=\"s\">14&nbsp;&nbsp;耶稣定睛一看，向他们说：「你们去，叫司祭们检验你们罢！」他们去的时候，便洁净了。</p><p class=\"s\">15&nbsp;&nbsp;其中一个，看见自己痊愈了，就回来大声光荣天主，</p><p class=\"s\">16&nbsp;&nbsp;并且跪伏在耶稣足前，感谢他；他是一个撒玛黎雅人。</p><p class=\"s\">17&nbsp;&nbsp;耶稣便说道：「洁净了的不是十个人吗？那九个人在那里呢？</p><p class=\"s\">18&nbsp;&nbsp;除了这个外邦人，就没有别人回来归光荣于天主吗？」</p><p class=\"s\">19&nbsp;&nbsp;耶稣遂给那人说：「起来，去罢！你的信德救了你。」</p><p class=\"t3\">天国的来临</p><p class=\"s\">20&nbsp;&nbsp;法利塞人问耶稣天主的国何时要来；耶稣回答说：「天主国的来临，并非是显然可见的；</p><p class=\"s\">21&nbsp;&nbsp;人也不能说：看呀，在这里；或：在那里。因为天主的国就在你们中间。」</p><p class=\"s\">22&nbsp;&nbsp;耶稣对门徒说：「日子将到，那时，你们切望看见人子日子中的一天，而不得见。</p><p class=\"s\">23&nbsp;&nbsp;人要向你们说：看呀，在那里；看呀，在这里。你们不要去，也不要追随，</p><p class=\"s\">24&nbsp;&nbsp;因为犹如闪电由天这边闪起，直照到天那边：人子在他的日子里，也要这样。</p><p class=\"s\">25&nbsp;&nbsp;但他必须先受许多苦，且被这一代所摈弃。</p><p class=\"s\">26&nbsp;&nbsp;在诺厄的日子里怎样，在人子的日子里也要怎样；</p><p class=\"s\">27&nbsp;&nbsp;那时，人们吃喝婚嫁，直到诺厄进入方舟的那天，洪水来了，消灭了所有的人。</p><p class=\"s\">28&nbsp;&nbsp;又如在罗特的日子里，人们吃喝买卖，种植建造，</p><p class=\"s\">29&nbsp;&nbsp;但在罗特从索多玛出来的那天，火及硫磺自天降下，消灭了所有的人：</p><p class=\"s\">30&nbsp;&nbsp;在人子显现的日子里，也要这样。</p><p class=\"s\">31&nbsp;&nbsp;在那一日，那在屋顶上，而他的器具在屋内的，不要下来取；那在田地里的，同样不要回来。</p><p class=\"s\">32&nbsp;&nbsp;你们要记得罗特的妻子！</p><p class=\"s\">33&nbsp;&nbsp;不论谁，若想保全自己的性命，必要丧失性命；凡丧失性命的，必要保存性命。</p><p class=\"s\">34&nbsp;&nbsp;我告诉你们：在这一夜，两个人同在一张床上，一个要被提去，而一个要被遗弃；</p><p class=\"s\">35&nbsp;&nbsp;两个女人一起推磨，一个要被提去，而一个要被遗弃。」＊</p><p class=\"s\">36&nbsp;&nbsp;他们问耶稣说：「主，在那里呢？」耶稣回答说：「在那里有尸体，老鹰就聚集在那里。」</p>"}