{"ptitle":"旧约 箴言篇 Proverbs","purl":"/bible/template/024","title":"旧约 箴言篇 Proverbs 第二十一章","url":"/bible/chapter/024/021.json","mp3":"/024/021.mp3","text":"<h2></h2><h3>旧约 箴言篇 Proverbs 第二十一章</h3><p class=\"t3\">上主鉴察人心</p><p class=\"s\">01.\t君王的心在上主手，有如水流，可随意转移。</p><p class=\"s\">02.\t人对自己的行为，都自觉正直；但审察人心的，却是上主。</p><p class=\"s\">03.\t秉公行义，比献祭献更悦上主。</p><p class=\"s\">04.\t傲慢的眼睛，骄傲的心灵，恶人的炫耀，无非是罪恶。</p><p class=\"s\">05.\t熟思的人，必足以致富；草率的人，必贫困缠身。</p><p class=\"t3\">作恶是害己</p><p class=\"s\">06.\t以谎言伪语骗得的财宝，是浮云轻烟，死亡的罗网。</p><p class=\"s\">07.\t恶人的暴戾，必殃及自身，因他们不肯去履行正义。</p><p class=\"s\">08.\t恶人的道路，歪曲邪僻；正人的行为，正直适中。</p><p class=\"s\">09.\t宁愿住在屋顶的一角，不愿与吵妇同居一室。</p><p class=\"s\">10.\t恶人的心灵，只求邪恶；对自己友伴，毫不关怀。</p><p class=\"s\">11.\t轻狂人遭受处罚，幼稚者将得明智；智慧人接受教训，更增加自己知识。</p><p class=\"s\">12.\t正义的上主监视恶人的家，且使恶人们都陷於灾祸中。</p><p class=\"t3\">为人应正义</p><p class=\"s\">13.\t谁对穷人的哀求，充耳不闻，他呼求时，也不会得到应允。</p><p class=\"s\">14.\t暗中相送的馈赠，可平息忿怒；投入怀中的礼物，可平息狂怒。</p><p class=\"s\">15.\t秉公行义，能叫义人喜乐；但为作恶的人，却是恐惧。</p><p class=\"s\">16.\t凡远离明智道路的人，必居於幽灵的集会中。</p><p class=\"s\">17.\t贪爱享乐的人，必遭受穷困；喜爱酒油的人，必不会致富。</p><p class=\"s\">18.\t恶人必将为义人作赎金，败类也将替君子作代价。</p><p class=\"s\">19.\t与好争易怒的女人同居，倒不如独自住在旷野。</p><p class=\"s\">20.\t珍贵的宝藏和油，积藏在智者家；但糊涂愚昧的人，却将之消耗净尽。</p><p class=\"s\">21.\t追求正义和仁慈的人，必将获得生命与尊荣。</p><p class=\"s\">22.\t智者必登上勇士的城邑，攻破城邑所凭倚的保垒。</p><p class=\"s\">23.\t谁谨守自己的口舌，心灵必能免受烦恼。</p><p class=\"s\">24.\t高傲的人名叫「狂人」，他行事必极端蛮横。</p><p class=\"s\">25.\t怠惰人的手不肯操作，必为他的愿望所扼杀。</p><p class=\"s\">26.\t贪婪的人，终日贪婪；正义的人，广施不吝。</p><p class=\"s\">27.\t恶人的祭献，已是可憎；若怀恶而献，更将如何？</p><p class=\"s\">28.\t作假见证的人，必要灭亡；但善於听的人，可常言。</p><p class=\"s\">29.\t邪恶的人，常装腔作势；正直的人，却举止检点。</p><p class=\"s\">30.\t任何智慧、才略或计谋，都不能与上主相对抗。</p><p class=\"s\">31.\t招兵买马，是为作作战之日；但是胜利，却由上主指使。</p>"}