{"ptitle":"旧约 箴言篇 Proverbs","purl":"/bible/template/024","title":"旧约 箴言篇 Proverbs 第十五章","url":"/bible/chapter/024/015.json","mp3":"/024/015.mp3","text":"<h2></h2><h3>旧约 箴言篇 Proverbs 第十五章</h3><p class=\"t3\">待人接物要温和</p><p class=\"s\">1&nbsp;&nbsp;温和的回答，平息忿怒；激昂的言语，使人动怒。</p><p class=\"s\">2&nbsp;&nbsp;智慧者的舌，广传智慧；愚昧人的口，吐露愚昧。</p><p class=\"s\">3&nbsp;&nbsp;上主的眼目，处处都在；善人和恶人，他都监视。</p><p class=\"s\">4&nbsp;&nbsp;抚慰的言辞，有如生命树；刻薄的言语，能刺伤人心。</p><p class=\"s\">5&nbsp;&nbsp;愚蠢的人，轻视父亲的管教；遵守规劝的，为人必精明。</p><p class=\"s\">6&nbsp;&nbsp;在义人家里，财产丰富；恶人的收入，必遭毁灭。</p><p class=\"s\">7&nbsp;&nbsp;智慧人的唇，散播智识；愚昧人的人，实不可靠。</p><p class=\"s\">8&nbsp;&nbsp;上主厌恶恶人的祭献，却喜悦正直人的祈祷。</p><p class=\"s\">9&nbsp;&nbsp;上主厌恶恶人的道路，却喜爱追求正义的人。</p><p class=\"s\">10&nbsp;&nbsp;离弃正道的，必遭严罚；憎恨规劝的，只有死亡。</p><p class=\"s\">11&nbsp;&nbsp;阴府和冥域，都明摆在上主面前，何况世人的心怀！</p><p class=\"s\">12&nbsp;&nbsp;轻狂者不爱受人指责，也不愿与智慧人往来。</p><p class=\"t3\">心安的幸福</p><p class=\"s\">13&nbsp;&nbsp;心中愉快，使面容焕发，心中悲伤，精神即颓丧。</p><p class=\"s\">14&nbsp;&nbsp;明达人的心，寻求智识；愚昧人的口，饱食昏愚。</p><p class=\"s\">15&nbsp;&nbsp;心情忧伤的，日日困坐愁城；心胸畅快的，时时如享喜宴。</p><p class=\"s\">16&nbsp;&nbsp;少有财宝而敬畏上主，胜于富有财宝而诸多烦恼。</p><p class=\"s\">17&nbsp;&nbsp;有情吃蔬菜，胜于无情食肥牛。</p><p class=\"s\">18&nbsp;&nbsp;易怒的人，常引起争端；含忍的人，却平息争论。</p><p class=\"s\">19&nbsp;&nbsp;懒惰人的道路，有如荆棘篱笆；正直人的行径，却是康庄大道。</p><p class=\"s\">20&nbsp;&nbsp;智慧的儿子，是父亲的喜乐；只有愚昧人，轻视自己的母亲。</p><p class=\"s\">21&nbsp;&nbsp;无知的人，以愚昧为乐；明智的人，却直道而行。</p><p class=\"s\">22&nbsp;&nbsp;缺乏考虑，计划必要失败；谋士众多，策略方克有成。</p><p class=\"s\">23&nbsp;&nbsp;应对得当，自觉快慰；言语适时，何其舒畅！</p><p class=\"s\">24&nbsp;&nbsp;生命之路使明智人向上，为此他能避免向下的阴府。</p><p class=\"t3\">上主爱恶的人</p><p class=\"s\">25&nbsp;&nbsp;上主将拆毁骄傲人的房屋，却要坚定寡妇的地界。</p><p class=\"s\">26&nbsp;&nbsp;邪恶的阴谋，为上主所憎恶；温良的言语，却为他所喜悦。</p><p class=\"s\">27&nbsp;&nbsp;贪求财货的，困扰自己的家庭；憎恶馈赠的，生活必能安定。</p><p class=\"s\">28&nbsp;&nbsp;义人的心，只默思善事；恶人的口，只吐露恶语。</p><p class=\"s\">29&nbsp;&nbsp;上主远离恶人，却俯听义人的祈祷。</p><p class=\"s\">30&nbsp;&nbsp;晶莹的目光，使人心旷神怡；美好的讯息，使人筋骨壮健。</p><p class=\"s\">31&nbsp;&nbsp;喜听有益生命劝戒的人，必得列于智慧人的中间。</p><p class=\"s\">32&nbsp;&nbsp;避免教导的，是作贱自己；听从规劝的，必获得机智。</p><p class=\"s\">33&nbsp;&nbsp;敬畏上主，是智慧的导师；谦卑自下，是荣耀的先声。</p>"}