{"ptitle":"旧约 艾斯德尔传","purl":"/bible/template/019","title":"旧约 艾斯德尔传 第五章","url":"/bible/chapter/019/005.json","mp3":"/019/005.mp3","text":"<h2></h2><h3>旧约 艾斯德尔传 第五章</h3><p class=\"s\">1&nbsp;&nbsp;第三天，艾斯德尔祈祷完毕，脱去苦衣麻服，穿上艳丽服装，</p><p class=\"s\">2&nbsp;&nbsp;刻意装饰打扮，又呼求了鉴临万物，拯救众生的天主，就带了两个婢女：一个扶着她那弱不禁风的身体；另一个尾随于后，扯起她的长裙。</p><p class=\"s\">3&nbsp;&nbsp;她体态轻盈，容貌娇艳，令人喜爱；但她此时却心惊胆战。</p><p class=\"s\">4&nbsp;&nbsp;经过几道宫门，来到君王前；此时君王正高坐龙椅，身着蟒袍玉带，金璧辉煌，使人一见生畏。</p><p class=\"s\">5&nbsp;&nbsp;君王抬起头来，见王后前来，龙颜大变，怒目而视；王后登时吓的昏迷，面无人色，倒在随侍她的婢女身上。</p><p class=\"s\">6&nbsp;&nbsp;但天主忽然转变了君王的心，使他的态度转为和颜悦色，急忙跑下龙椅，双手把她抱住，及至王后苏醒，王便以温和的言语抚慰她说：</p><p class=\"s\">7&nbsp;&nbsp;「艾斯德尔，你有什么事？我是你哥哥，尽管放心好了！你不至于死，王法只是限于属下。请上前来！」</p><p class=\"s\">8&nbsp;&nbsp;于是拿起金杖，放在她颈上，且吻她说：「向我说罢！」</p><p class=\"s\">9&nbsp;&nbsp;她答说：「我主，我见了你，好像见了天主的使者；一见你的威仪，我就心神慌乱了。</p><p class=\"s\">10&nbsp;&nbsp;我主，你实令人惊奇，仪容又和蔼可亲。」</p><p class=\"s\">11&nbsp;&nbsp;她正在说话时，又晕倒了。君王因此十分担心，众臣仆便都设法使她苏醒过来。</p><p class=\"s\">12&nbsp;&nbsp;第三天，艾斯德尔身穿王后的华服，站在王宫的内院，面向宫殿；那时君王正坐在宫殿的宝座上，面向宫门。</p><p class=\"s\">13&nbsp;&nbsp;君王一见艾斯德尔王后在庭院内，就对她起了宠幸的心，于是向艾斯德尔伸出手中的金杖，艾斯德尔遂上前来，摸了金杖的顶端。</p><p class=\"s\">14&nbsp;&nbsp;君王问她说：「艾斯德尔后，你有什么事？你要求什么？即使要求一半江山，我也必赐给你！」</p><p class=\"s\">15&nbsp;&nbsp;艾斯德尔答说：「若大王开恩，请大王今日与哈曼同去饮妾为陛下所预备的酒宴。」</p>"}