{"ptitle":"旧约 圣咏集","purl":"/bible/template/023","title":"旧约 圣咏集 第卅六篇人的邪恶与天主的慈爱","url":"/bible/chapter/023/036.json","mp3":"/023/036.mp3","text":"<h2></h2><h3>旧约 圣咏集 第卅六篇人的邪恶与天主的慈爱</h3><p class=\"s\">01.\t上主的仆人达味作，交与乐官。</p><p class=\"s\">02.\t恶人从心就喜爱不义，他毫无敬畏天主的诚意。</p><p class=\"s\">03.\t他只是在自己的心自慰：无人发现他的罪，无人惩治。</p><p class=\"s\">04.\t他满口尽是虚伪与诈欺，早已把智慧与善行抛弃。</p><p class=\"s\">05.\t他在床上筹画作恶，立於邪道，不怕罪过。</p><p class=\"s\">06.\t上主，你的慈爱高达青天，你的忠诚上彻云间。</p><p class=\"s\">07.\t你的正义有如摩天的高山，你的公平有如无底的深渊；上主，是你使人畜生命安全。</p><p class=\"s\">08.\t天主，你的慈爱多么可贵可珍，人子们都向你的护翼下投奔。</p><p class=\"s\">09.\t他们不但饱尝你宫殿中的盛筵，你还赐他们畅饮你怡人的溪川。</p><p class=\"s\">10.\t因为在你那有生命的泉源，藉你的光明才能把光明看见。</p><p class=\"s\">11.\t求你为恭敬你的人保留恩宠，并为心地正直的人保持公平。</p><p class=\"s\">12.\t求你不要高傲人的脚践踏我，求你不要让罪恶人的手骚扰我。</p><p class=\"s\">13.\t请看！作恶的人己经一败涂地，他们既已倾倒，无法重新兴起。</p>"}