{"ptitle":"新约 若望福音 John","purl":"/bible/template/050","title":"新约 若望福音 John 第十一章","url":"/bible/chapter/050/011.json","mp3":"/050/011.mp3","text":"<h2></h2><h3>新约 若望福音 John 第十一章</h3><p class=\"t3\">拉匝禄病死</p><p class=\"s\">01.\t有一个病人，名叫拉匝禄，住在伯达尼，即玛利亚和她姊姊玛尔大所住的村庄。</p><p class=\"s\">02.\t玛利亚就是那曾用香液傅抹过主，并用自己的头发擦乾过他脚的妇人，患病的拉匝禄是他的兄弟。</p><p class=\"s\">03.\t他们姊妹二人便派人到耶稣那说:「主啊!你所爱的病了!」</p><p class=\"s\">04.\t耶稣听了便说:「这病不致於死，只是为彰显天主的光荣，并为叫天主子因此受到光荣。」</p><p class=\"s\">05.\t耶稣素爱玛尔大及她的妹妹和拉匝禄。</p><p class=\"s\">06.\t当他听说拉匝禄病了，仍在原地逗留了两天。</p><p class=\"s\">07.\t此后，才对门徒说:「我们再往犹太去罢!」</p><p class=\"s\">08.\t门徒向他说:「辣彼，近来犹太人图谋砸死你，你又要往那去么？」</p><p class=\"s\">09.\t耶稣回答说:「白日不是有十二个时辰么?人若在白日行路，不会碰跌，因为看得见这世界的光；</p><p class=\"s\">10.\t人若在黑夜行路，就要碰跌，因为他没有光。」</p><p class=\"s\">11.\t耶稣说了这些话，又给他们说:「我们的朋友拉匝禄睡着了，我要去叫醒他。」</p><p class=\"s\">12.\t门徒便对他说:「主，若是他睡着了，必定好了。」</p><p class=\"s\">13.\t耶稣原是指他的死说的，他们却以为他是指安眠睡觉说的。</p><p class=\"s\">14.\t然后，耶稣就明明地向他们说:「拉匝禄死了。</p><p class=\"s\">15.\t为了你们，我喜欢我不在那，好叫你们相信；我们到他那去罢!」</p><p class=\"s\">16.\t号称狄狄摩的多默便向其他的同伴说:「我们也去，同他一起死罢!」</p><p class=\"t3\">拉匝禄复活</p><p class=\"s\">17.\t耶稣一到伯达尼，得知拉匝禄在坟墓已经四天了。</p><p class=\"s\">18.\t伯达尼靠近耶路撒冷，相距约十五「斯塔狄」，</p><p class=\"s\">19.\t因而有许多犹太人来到玛尔大和玛利亚那，为她们兄弟的死安慰她们。</p><p class=\"s\">20.\t玛尔大一听说耶稣来了，便去迎接他；玛利亚仍坐在家。</p><p class=\"s\">21.\t玛尔大对耶稣说:「若是你在这，我的兄弟决不会死!</p><p class=\"s\">22.\t就是现在，我也知道:你无论向天主求什么，天主必要赐给你。」</p><p class=\"s\">23.\t耶稣对她说:「你的兄弟必定要复活。」</p><p class=\"s\">24.\t玛尔大说:「我知道在末日复活时，他必要复活。」</p><p class=\"s\">25.\t耶稣对她说:「我就是复活，就是生命；信从我的，即使死了，仍要活着；</p><p class=\"s\">26.\t凡活着而信从我的人，必永远不死。你信么？」</p><p class=\"s\">27.\t她回答说:「是的，主，我信你是默西亚，天主子，要来到世界上的那一位。」</p><p class=\"s\">28.\t她说了这话，就去叫她的妹妹玛利亚，偷偷地说:「师傅来了，他叫你。」</p><p class=\"s\">29.\t玛利亚一听说，立时起身到耶稣那去了。</p><p class=\"s\">30.\t那时，耶稣还没有进村庄，仍在玛尔大迎接他的地方。</p><p class=\"s\">31.\t那些同玛利亚在家，安慰他的犹太人，见她急忙起身出去，便跟着她，以为她往坟墓上去哭泣。</p><p class=\"s\">32.\t当玛利亚来到耶稣所在的地方，一看见他，就俯伏在他脚前，向他说:「主!若是你在这，我的兄弟决不会死!」</p><p class=\"s\">33.\t耶稣看见她哭泣，还有同他一起来的犹太人也哭泣，便心神感伤，难过起来，</p><p class=\"s\">34.\t遂说:「你们把他安放在那？」他们回答说:「主，你来，看罢!」</p><p class=\"s\">35.\t耶稣流泪了。</p><p class=\"s\">36.\t於是犹太人说:「看，他多么爱他啊!」</p><p class=\"s\">37.\t其中有些人说:「这个开了瞎子眼睛的，岂不能使这人也不死么？」</p><p class=\"s\">38.\t耶稣心中又感伤起来，来到坟墓前。这坟墓是个洞穴，前面有一块石头堵着。</p><p class=\"s\">39.\t耶稣说：「挪开这块石头!」死者的姊姊玛尔大向他说:「主!已经臭了，因为已有四天了。」</p><p class=\"s\">40.\t耶稣对她说:「我不是告诉过你:如果你信，会看到天主的光荣吗？」</p><p class=\"s\">41.\t他们便挪开了石头；耶稣举目向上说:「父啊!我感谢你，因为你俯听了我。</p><p class=\"s\">42.\t我本来知道你常常俯听我，但是我说这话，是为了四周站立的群众，好叫他们信是你派遣了我。」</p><p class=\"s\">43.\t说完这话，便大声喊说:「拉匝禄!出来罢!」</p><p class=\"s\">44.\t死者便出来了，脚和手都缠着布条，面上还蒙着汗巾。耶稣向他们说:「解开他，让他行走罢。」</p><p class=\"t3\">公议会决议杀害耶稣</p><p class=\"s\">45.\t那些来到玛利亚那的犹太人，一看到耶稣所行的事，就有许多人信了他</p><p class=\"s\">46.\t他们中也有一些到法利塞人那去，把耶稣所行的，报告给他们。</p><p class=\"s\">47.\t因此，司祭长和法利塞人召集了会议说:「这人行了许多奇迹，我们怎么办呢？</p><p class=\"s\">48.\t如果让他这样，众都会信从，罗马人必要来，连我们的圣殿和民族都除掉。」</p><p class=\"s\">49.\t他们中有一个名叫盖法的，正是那一年的大司祭，对他们说:「你们什么都不懂，</p><p class=\"s\">50.\t也不想想:叫一个人替百姓死，以免全民族灭亡；这为你们多么有利。」</p><p class=\"s\">51.\t这话不是由他自己说出的，只因他是那年的大司祭，才预言了耶稣将为民族而死；</p><p class=\"s\">52.\t不但为犹太民族，而且也是为使那四散的天主的儿女都聚集归一。</p><p class=\"s\">53.\t从那一天起，他们就议决要杀害耶稣。</p><p class=\"s\">54.\t因此，耶稣不再公开地在犹太人中往来，却从那往临近荒野的地方去，来到一座名叫厄弗辣因的城，在那里和他的门徒住下了。</p><p class=\"s\">55.\t犹太人的逾越节临近了，所以，许多人在逾越节前，从乡间上了耶路撒冷，要圣洁自己。</p><p class=\"s\">56.\t他们就寻找耶稣，并站在圣殿内，彼此谈论说:「你们想什么？他来不来过节呢？」</p><p class=\"s\">57.\t司祭长和法利塞人早已颁发命令:如果有人知道他在那里，就该通知他们，好去捉拿他。</p>"}